pic2map-0.1.0.dist-info/entry_points.txt
pic2map-0.1.0.dist-info/WHEEL
pic2map-0.1.0.dist-info/METADATA
pic2map-0.1.0.dist-info/top_level.txt
pic2map-0.1.0.dist-info/DESCRIPTION.rst
pic2map-0.1.0.dist-info/metadata.json
pic2map-0.1.0.dist-info/RECORD
pic2map/cli.py
pic2map/__init__.py
pic2map/fs.py
pic2map/gps.py
pic2map/db.py
pic2map/server/templates/index.html
pic2map/server/static/main.js
pic2map/server/static/main.css
