Metadata-Version: 2.0
Name: pic2map
Version: 0.1.0
Summary: Display pictures location in a map
Home-page: https://github.com/jcollado/pic2map
Author: Javier Collado
Author-email: jcollado@nowsecure.com
License: MIT
Keywords: picture map location
Platform: UNKNOWN
Classifier: Development Status :: 3 - Alpha
Classifier: Intended Audience :: Developers
Classifier: License :: OSI Approved :: MIT License
Classifier: Natural Language :: English
Classifier: Programming Language :: Python :: 2.7
Requires-Dist: Flask
Requires-Dist: PyExifTool
Requires-Dist: SQLAlchemy
Requires-Dist: arrow
Requires-Dist: python-magic
Requires-Dist: pyxdg
Requires-Dist: voluptuous
